{
  "poc_database.customers": {
    "fields": [
      {
        "keyId": "b'\\xae]\\x0bC\\xd9\\xceM\\xec\\xa5e\\xd2\\xff\\x1c\\xad\\xe4\\xad'",
        "path": "searchable_name",
        "bsonType": "string",
        "queries": [
          {
            "queryType": "substringPreview",
            "min": 2,
            "max": 10,
            "strMinQueryLength": 2,
            "strMaxQueryLength": 10,
            "strMaxLength": 60,
            "caseSensitive": false,
            "diacriticSensitive": false
          }
        ]
      },
      {
        "keyId": "b'\\xa3*\\xe3\\xf0\\xf2\\xf6M\\x14\\x93[\\xba\\xe8\\xff\\xde=\\xa5'",
        "path": "searchable_email",
        "bsonType": "string",
        "queries": [
          {
            "queryType": "prefixPreview",
            "min": 1,
            "max": 30,
            "strMinQueryLength": 1,
            "strMaxQueryLength": 50,
            "strMaxLength": 100,
            "caseSensitive": false,
            "diacriticSensitive": false
          }
        ]
      },
      {
        "keyId": "b'\\xb4\\x11N\\x1b\\xb9\\xa2IB\\xbf3\\xb05\\x9bS\\x82;'",
        "path": "searchable_phone",
        "bsonType": "string",
        "queries": [
          {
            "queryType": "equality"
          }
        ]
      },
      {
        "keyId": "b't\\x16{\\x04\\x8c\\x19LY\\x91\\xc6\\xeaQ\\x0e\\xec\\xd4\\x19'",
        "path": "metadata.category",
        "bsonType": "string",
        "queries": [
          {
            "queryType": "equality"
          }
        ]
      },
      {
        "keyId": "b'\\x07ZP\\xa5\\xd4\\xd3CP\\xb6\\t\\xf8Q\\xf1\\xcb`s'",
        "path": "metadata.status",
        "bsonType": "string",
        "queries": [
          {
            "queryType": "equality"
          }
        ]
      }
    ]
  }
}